djc_ext_pydantic-1.1.0.dist-info/licenses/LICENSE
djc_pydantic/__init__.py
djc_pydantic/extension.py
djc_pydantic/monkeypatch.py
djc_pydantic/py.typed
djc_pydantic/utils.py
djc_ext_pydantic-1.1.0.dist-info/METADATA
djc_ext_pydantic-1.1.0.dist-info/WHEEL
djc_ext_pydantic-1.1.0.dist-info/top_level.txt
djc_ext_pydantic-1.1.0.dist-info/RECORD
