Metadata-Version: 2.4
Name: djc-ext-pydantic
Version: 1.1.0
Summary: Input validation with Pydantic for Django Components
Author-email: Juro Oravec <juraj.oravec.josefson@gmail.com>
License: MIT
Project-URL: Homepage, https://github.com/django-components/djc-ext-pydantic/
Keywords: pydantic,django-components,djc,django,components
Classifier: Framework :: Django
Classifier: Framework :: Django :: 4.2
Classifier: Framework :: Django :: 5.0
Classifier: Framework :: Django :: 5.1
Classifier: Operating System :: OS Independent
Classifier: Programming Language :: Python
Classifier: Programming Language :: Python :: 3
Classifier: Programming Language :: Python :: 3.8
Classifier: Programming Language :: Python :: 3.9
Classifier: Programming Language :: Python :: 3.10
Classifier: Programming Language :: Python :: 3.11
Classifier: Programming Language :: Python :: 3.12
Classifier: Programming Language :: Python :: 3.13
Classifier: Environment :: Web Environment
Classifier: Topic :: Internet :: WWW/HTTP
Classifier: Topic :: Internet :: WWW/HTTP :: Dynamic Content
Classifier: Intended Audience :: Developers
Classifier: License :: OSI Approved :: MIT License
Requires-Python: <4.0,>=3.8
License-File: LICENSE
Requires-Dist: django-components>=0.140
Requires-Dist: pydantic>=2.9
Dynamic: license-file
